macos_trackpad_pressure-0.1.2.dist-info/licenses/LICENSE
trackpad_pressure/__init__.py
trackpad_pressure/__main__.py
trackpad_pressure/gui.py
trackpad_pressure/monitor.py
macos_trackpad_pressure-0.1.2.dist-info/METADATA
macos_trackpad_pressure-0.1.2.dist-info/WHEEL
macos_trackpad_pressure-0.1.2.dist-info/entry_points.txt
macos_trackpad_pressure-0.1.2.dist-info/top_level.txt
macos_trackpad_pressure-0.1.2.dist-info/RECORD
