Metadata-Version: 2.4
Name: macos-trackpad-pressure
Version: 0.1.2
Summary: Monitor and capture Force Touch trackpad pressure on macOS
Home-page: https://github.com/9nesh/trackforce
Author: Inesh Tickoo
Author-email: Inesh Tickoo <itickoo@owu.edu>
License: MIT
Project-URL: Homepage, https://github.com/9nesh/trackforce
Project-URL: Repository, https://github.com/9nesh/trackforce
Project-URL: Issues, https://github.com/9nesh/trackforce/issues
Keywords: macos,trackpad,pressure,force-touch,pyobjc,sensor
Classifier: Development Status :: 3 - Alpha
Classifier: Intended Audience :: Developers
Classifier: Intended Audience :: Education
Classifier: Intended Audience :: Science/Research
Classifier: Topic :: Software Development :: Libraries :: Python Modules
Classifier: Topic :: Scientific/Engineering :: Human Machine Interfaces
Classifier: Topic :: System :: Hardware :: Hardware Drivers
Classifier: Topic :: Multimedia :: Graphics
Classifier: Environment :: MacOS X :: Cocoa
Classifier: License :: OSI Approved :: MIT License
Classifier: Natural Language :: English
Classifier: Operating System :: MacOS :: MacOS X
Classifier: Programming Language :: Python :: 3
Requires-Python: >=3.7
License-File: LICENSE
Requires-Dist: pyobjc-framework-Cocoa>=9.0
Dynamic: author
Dynamic: home-page
Dynamic: license-file
Dynamic: requires-python
